{"ResultCount":1,"Search":{"KodeEmiten":"BCAP","EmitenType":null,"SortOrder":null,"SortColumn":null,"indexfrom":1,"pagesize":1},"Profiles":[{"Alamat":"MNC Financial Center Lt.21\r\nJl. Kebon Sirih No.21-27\r\nJakarta Pusat. 10340\r\nIndonesia","BAE":"","DataID":0,"Divisi":null,"EfekEmiten_EBA":false,"EfekEmiten_ETF":false,"EfekEmiten_Obligasi":true,"EfekEmiten_Saham":true,"EfekEmiten_SPEI":false,"Industri":"Perusahaan Holding & Investasi","SubIndustri":"Perusahaan Holding Keuangan","Email":"corsec.mncfinancialservices@mncgroup.com","Fax":"021-39836886","id":0,"JenisEmiten":null,"KegiatanUsahaUtama":"Investment Company","KodeDivisi":null,"KodeEmiten":"BCAP","NamaEmiten":"MNC Kapital Indonesia Tbk","NPKP":"","NPWP":"01.911.968.4-054.000","PapanPencatatan":"Utama","Sektor":"Keuangan","SubSektor":"Perusahaan Holding & Investasi","TanggalPencatatan":"2001-06-08T00:00:00","Telepon":"021-29709700","Website":"www.mncfinancialservices.com","Status":0,"Logo":"/Portals/0/StaticData/ListedCompanies/LogoEmiten/BCAP.jpg"}],"Sekretaris":[{"Nama":"Edward Kennetze Lubis","Telepon":"021-29709700","Website":null,"Email":"edward.lubis@mncgroup.com","Fax":"021-39836870","HP":""}],"Direktur":[{"Nama":"Mashudi Hamka","Jabatan":"DIREKTUR UTAMA","Afiliasi":true},{"Nama":"Jessica Herliani Tanoesoedibjo","Jabatan":"DIREKTUR","Afiliasi":true},{"Nama":"Ageng Purwanto","Jabatan":"DIREKTUR","Afiliasi":true},{"Nama":"Peter Fajar","Jabatan":"DIREKTUR","Afiliasi":true},{"Nama":"Oerianto Guyandi","Jabatan":"DIREKTUR","Afiliasi":true},{"Nama":"Muhammad Suhada","Jabatan":"DIREKTUR","Afiliasi":true},{"Nama":"Mahdan","Jabatan":"DIREKTUR","Afiliasi":true}],"Komisaris":[{"Nama":"Wito Mailoa","Jabatan":"KOMISARIS UTAMA","Independen":false},{"Nama":"Tien","Jabatan":"KOMISARIS","Independen":false},{"Nama":"Sukisto","Jabatan":"KOMISARIS","Independen":true}],"KomiteAudit":[{"Jabatan":"KETUA","Nama":"Sukisto"},{"Jabatan":"ANGGOTA","Nama":"Andrea Frans Tambunan"},{"Jabatan":"ANGGOTA","Nama":"Riza Satria"}],"PemegangSaham":[{"Jumlah":21228044760.0,"Kategori":"Lebih dari 5%","Nama":"PT MNC Asia Holding Tbk (d/h. PT MNC Investama Tbk)","Pengendali":true,"Persentase":49.81},{"Jumlah":3900000000.0,"Kategori":"Lebih dari 5%","Nama":"Jalan Pantai Limited","Pengendali":false,"Persentase":9.15},{"Jumlah":3708705000.0,"Kategori":"Lebih dari 5%","Nama":"HT Investment Development Ltd 2","Pengendali":false,"Persentase":8.7},{"Jumlah":2844091300.0,"Kategori":"Lebih dari 5%","Nama":"UOB Kay Hian (Hong Kong) Ltd","Pengendali":false,"Persentase":6.67},{"Jumlah":10938009867.0,"Kategori":"Kurang dari 5%","Nama":"Masyarakat","Pengendali":false,"Persentase":25.67},{"Jumlah":0.0,"Kategori":"Saham Treasury","Nama":"Saham Treasury","Pengendali":false,"Persentase":0.0},{"Jumlah":24309100.0,"Kategori":"Komisaris","Nama":"Tien","Pengendali":false,"Persentase":0.06},{"Jumlah":6486100.0,"Kategori":"Direksi","Nama":"Mashudi Hamka","Pengendali":false,"Persentase":0.02},{"Jumlah":50727500.0,"Kategori":"Direksi","Nama":"Jessica Herliani Tanoesoedibjo","Pengendali":false,"Persentase":0.12},{"Jumlah":5050000.0,"Kategori":"Direksi","Nama":"Oerianto Guyandi","Pengendali":false,"Persentase":0.01},{"Jumlah":4922800.0,"Kategori":"Direksi","Nama":"Ageng Purwanto","Pengendali":false,"Persentase":0.01},{"Jumlah":3936100.0,"Kategori":"Direksi","Nama":"Peter Fajar","Pengendali":false,"Persentase":0.01},{"Jumlah":452500.0,"Kategori":"Direksi","Nama":"Muhammad Suhada","Pengendali":false,"Persentase":0.0}],"AnakPerusahaan":[{"BidangUsaha":"Jasa Perantara pedagang efek dan penjamin emisi","JumlahAset":76216.0,"Lokasi":"United States of America","MataUang":"IDR","Nama":"Auerbach Grayson Ltd (AGCO)","Persentase":75.0,"Satuan":"JUTAAN","StatusOperasi":"Aktif","TahunKomersil":"1990"},{"BidangUsaha":"Perusahaan Investasi","JumlahAset":868659.0,"Lokasi":"British Virgin Island","MataUang":"IDR","Nama":"Lafite Assets Ltd","Persentase":100.0,"Satuan":"JUTAAN","StatusOperasi":"Aktif","TahunKomersil":"2006"},{"BidangUsaha":"Perusahaan Investasi","JumlahAset":2.0,"Lokasi":"British Virgin Island","MataUang":"IDR","Nama":"Motion Digital Ltd","Persentase":99.99,"Satuan":"JUTAAN","StatusOperasi":"Belum Beroperasi","TahunKomersil":"2022"},{"BidangUsaha":"Penyewaan Properti","JumlahAset":106.0,"Lokasi":"Jakarta","MataUang":"IDR","Nama":"PT Bandung Nusantara Propertindo (BDNP)","Persentase":99.91999817,"Satuan":"JUTAAN","StatusOperasi":"Aktif","TahunKomersil":"2016"},{"BidangUsaha":"Bank","JumlahAset":11652904.0,"Lokasi":"Jakarta","MataUang":"IDR","Nama":"PT Bank MNC Internasional Tbk (BMNCI)","Persentase":50.43000031,"Satuan":"JUTAAN","StatusOperasi":"Aktif","TahunKomersil":"1989"},{"BidangUsaha":"Bank","JumlahAset":15348185.0,"Lokasi":"Jakarta","MataUang":"IDR","Nama":"PT Bank MNC Internasional Tbk (BMNCI)","Persentase":48.99,"Satuan":"JUTAAN","StatusOperasi":"Aktif","TahunKomersil":"1989"},{"BidangUsaha":"Teknologi Informasi","JumlahAset":83042.0,"Lokasi":"Jakarta","MataUang":"IDR","Nama":"PT Flash Mobile","Persentase":99.98999786,"Satuan":"JUTAAN","StatusOperasi":"Aktif","TahunKomersil":"2004"},{"BidangUsaha":"Teknologi Informasi","JumlahAset":73939.0,"Lokasi":"Jakarta","MataUang":"IDR","Nama":"PT Flash Mobile (FM)","Persentase":99.99,"Satuan":"JUTAAN","StatusOperasi":"Aktif","TahunKomersil":"2004"},{"BidangUsaha":"Penyewaan Properti","JumlahAset":167.0,"Lokasi":"Jakarta","MataUang":"IDR","Nama":"PT Makassar Nusantara Propertindo (MKNP)","Persentase":99.91999817,"Satuan":"JUTAAN","StatusOperasi":"Aktif","TahunKomersil":"2016"},{"BidangUsaha":"Penyewaan Properti","JumlahAset":28646.0,"Lokasi":"Jakarta","MataUang":"IDR","Nama":"PT Medan Nusantara Propertindo (MDNP)","Persentase":99.91999817,"Satuan":"JUTAAN","StatusOperasi":"Aktif","TahunKomersil":"2016"},{"BidangUsaha":"Penyewaan Properti","JumlahAset":77901.0,"Lokasi":"Jakarta","MataUang":"IDR","Nama":"PT Medan Nusantara Propertindo (MDNP)","Persentase":99.92,"Satuan":"JUTAAN","StatusOperasi":"Aktif","TahunKomersil":"2016"},{"BidangUsaha":"Jasa pengelolaan Investasi","JumlahAset":94677.0,"Lokasi":"Jakarta","MataUang":"IDR","Nama":"PT MNC Asset Management (MNCAM)","Persentase":99.99,"Satuan":"JUTAAN","StatusOperasi":"Aktif","TahunKomersil":"1999"},{"BidangUsaha":"Jasa pengelolaan Investasi","JumlahAset":79118.0,"Lokasi":"Jakarta","MataUang":"IDR","Nama":"PT MNC Asset Management (MNCAM)","Persentase":99.98999786,"Satuan":"JUTAAN","StatusOperasi":"Aktif","TahunKomersil":"1999"},{"BidangUsaha":"Jasa asuransi umum","JumlahAset":566735.0,"Lokasi":"Jakarta","MataUang":"IDR","Nama":"PT MNC Asuransi Indonesia (MNCAI)","Persentase":99.98000336,"Satuan":"JUTAAN","StatusOperasi":"Aktif","TahunKomersil":"1987"},{"BidangUsaha":"Jasa asuransi umum","JumlahAset":664361.0,"Lokasi":"Jakarta","MataUang":"IDR","Nama":"PT MNC Asuransi Indonesia (MNCAI)","Persentase":99.98,"Satuan":"JUTAAN","StatusOperasi":"Aktif","TahunKomersil":"1987"},{"BidangUsaha":"Lembaga Pembiayaan","JumlahAset":1384204.0,"Lokasi":"Jakarta","MataUang":"IDR","Nama":"PT MNC Finance (MNCF)","Persentase":99.99,"Satuan":"JUTAAN","StatusOperasi":"Aktif","TahunKomersil":"1989"},{"BidangUsaha":"Lembaga Pembiayaan","JumlahAset":1387363.0,"Lokasi":"Jakarta","MataUang":"IDR","Nama":"PT MNC Finance (MNCF)","Persentase":99.98999786,"Satuan":"JUTAAN","StatusOperasi":"Aktif","TahunKomersil":"1989"},{"BidangUsaha":"Jasa penyewaan","JumlahAset":614702.0,"Lokasi":"Jakarta","MataUang":"IDR","Nama":"PT MNC Guna Usaha Indonesia (MNCGUI)","Persentase":99.98999786,"Satuan":"JUTAAN","StatusOperasi":"Aktif","TahunKomersil":"1993"},{"BidangUsaha":"Jasa penyewaan","JumlahAset":658818.0,"Lokasi":"Jakarta","MataUang":"IDR","Nama":"PT MNC Guna Usaha Indonesia (MNCGUI)","Persentase":99.99,"Satuan":"JUTAAN","StatusOperasi":"Aktif","TahunKomersil":"1993"},{"BidangUsaha":"Jasa Perantara Asuransi","JumlahAset":3195.0,"Lokasi":"Jakarta","MataUang":"IDR","Nama":"PT MNC Insurance Broker","Persentase":99.99,"Satuan":"JUTAAN","StatusOperasi":"Aktif","TahunKomersil":"2021"},{"BidangUsaha":"Jasa asuransi jiwa","JumlahAset":408386.0,"Lokasi":"Jakarta","MataUang":"IDR","Nama":"PT MNC Life Assurance (MNCL)","Persentase":99.98,"Satuan":"JUTAAN","StatusOperasi":"Aktif","TahunKomersil":"1988"},{"BidangUsaha":"Jasa asuransi jiwa","JumlahAset":384396.0,"Lokasi":"Jakarta","MataUang":"IDR","Nama":"PT MNC Life Assurance (MNCL)","Persentase":99.98000336,"Satuan":"JUTAAN","StatusOperasi":"Aktif","TahunKomersil":"1988"},{"BidangUsaha":"Modal Ventura","JumlahAset":108.0,"Lokasi":"Jakarta","MataUang":"IDR","Nama":"PT MNC Modal Ventura","Persentase":99.92,"Satuan":"JUTAAN","StatusOperasi":"Aktif","TahunKomersil":"2016"},{"BidangUsaha":"Jasa Perantara pedagang efek dan penjamin emisi","JumlahAset":1829335.0,"Lokasi":"Jakarta","MataUang":"IDR","Nama":"PT MNC Sekuritas (MNCS)","Persentase":99.99,"Satuan":"JUTAAN","StatusOperasi":"Aktif","TahunKomersil":"2004"},{"BidangUsaha":"Jasa Perantara pedagang efek dan penjamin emisi","JumlahAset":2007016.0,"Lokasi":"Jakarta","MataUang":"IDR","Nama":"PT MNC Sekuritas (MNCS)","Persentase":99.98999786,"Satuan":"JUTAAN","StatusOperasi":"Aktif","TahunKomersil":"2004"},{"BidangUsaha":"Finansial Teknologi","JumlahAset":155319.0,"Lokasi":"Jakarta","MataUang":"IDR","Nama":"PT MNC Teknologi Nusantara (MTN)","Persentase":99.98999786,"Satuan":"JUTAAN","StatusOperasi":"Aktif","TahunKomersil":"2018"},{"BidangUsaha":"Finansial Teknologi","JumlahAset":183923.0,"Lokasi":"Jakarta","MataUang":"IDR","Nama":"PT MNC Teknologi Nusantara (MTN)","Persentase":99.99,"Satuan":"JUTAAN","StatusOperasi":"Aktif","TahunKomersil":"2018"},{"BidangUsaha":"Layanan Urun Dana","JumlahAset":2925.0,"Lokasi":"Jakarta","MataUang":"IDR","Nama":"PT Modal Anak Bangsa","Persentase":99.99,"Satuan":"JUTAAN","StatusOperasi":"Belum Beroperasi","TahunKomersil":"2016"},{"BidangUsaha":"Penyewaan Properti","JumlahAset":1489.0,"Lokasi":"Jakarta","MataUang":"IDR","Nama":"PT Modal Anak Bangsa (PT Surabaya Nusantara Propertindo (SBNP))","Persentase":99.91999817,"Satuan":"JUTAAN","StatusOperasi":"Aktif","TahunKomersil":"2016"},{"BidangUsaha":"Perdagangan Aset Digital","JumlahAset":10023.0,"Lokasi":"Jakarta","MataUang":"IDR","Nama":"PT Motion Crypto Technology (dahulu PT Bandung Nusantara Propertindo)","Persentase":99.92,"Satuan":"JUTAAN","StatusOperasi":"Belum Beroperasi","TahunKomersil":"2016"},{"BidangUsaha":"Perusahaan Investasi","JumlahAset":13500.0,"Lokasi":"Jakarta","MataUang":"IDR","Nama":"PT Motion Digital Technology","Persentase":99.99,"Satuan":"JUTAAN","StatusOperasi":"Belum Beroperasi","TahunKomersil":"2022"},{"BidangUsaha":"Penyewaan Properti","JumlahAset":113.0,"Lokasi":"Jakarta","MataUang":"IDR","Nama":"PT Palembang Nusantara Propertindo (PBNP)","Persentase":99.91999817,"Satuan":"JUTAAN","StatusOperasi":"Aktif","TahunKomersil":"2016"},{"BidangUsaha":"Penyewaan Properti","JumlahAset":7231.0,"Lokasi":"Jakarta","MataUang":"IDR","Nama":"PT Riau Nusantara Propertindo (RINP)","Persentase":99.91999817,"Satuan":"JUTAAN","StatusOperasi":"Aktif","TahunKomersil":"2016"},{"BidangUsaha":"Penyewaan Properti","JumlahAset":6708.0,"Lokasi":"Jakarta","MataUang":"IDR","Nama":"PT Riau Nusantara Propertindo (RINP)","Persentase":99.92,"Satuan":"JUTAAN","StatusOperasi":"Aktif","TahunKomersil":"2016"},{"BidangUsaha":"Penyewaan Properti","JumlahAset":111.0,"Lokasi":"Jakarta","MataUang":"IDR","Nama":"PT Semarang Nusantara Propertindo (SGNP)","Persentase":99.92,"Satuan":"JUTAAN","StatusOperasi":"Aktif","TahunKomersil":"2016"},{"BidangUsaha":"Penyewaan Properti","JumlahAset":112.0,"Lokasi":"Jakarta","MataUang":"IDR","Nama":"PT Semarang Nusantara Propertindo (SGNP)","Persentase":99.91999817,"Satuan":"JUTAAN","StatusOperasi":"Aktif","TahunKomersil":"2016"},{"BidangUsaha":"Finansial Teknologi","JumlahAset":11815.0,"Lokasi":"Jakarta","MataUang":"IDR","Nama":"PT Sistem Informasi Aplikasi Pembayaran","Persentase":99.99,"Satuan":"JUTAAN","StatusOperasi":"Aktif","TahunKomersil":"2016"},{"BidangUsaha":"Penyewaan Properti","JumlahAset":113.0,"Lokasi":"Jakarta","MataUang":"IDR","Nama":"PT Yogyakarta Nusantara Propertindo (YKNP)","Persentase":99.91999817,"Satuan":"JUTAAN","StatusOperasi":"Aktif","TahunKomersil":"2016"},{"BidangUsaha":"Perusahaan Investasi","JumlahAset":385283.0,"Lokasi":"British Virgin Island","MataUang":"IDR","Nama":"Winfly Ltd","Persentase":100.0,"Satuan":"JUTAAN","StatusOperasi":"Aktif","TahunKomersil":"2006"},{"BidangUsaha":"Perusahaan Investasi","JumlahAset":585914.0,"Lokasi":"British Virgin Island","MataUang":"IDR","Nama":"Winfly Ltd","Persentase":100.0,"Satuan":"JUTAAN","StatusOperasi":"Aktif","TahunKomersil":"2006"}],"KAP":[],"Dividen":[],"BondsAndSukuk":[],"IssuedBond":[{"KodeEmiten":"BCAP","NamaSeri":"-","AmortisasiValue":"-","SinkingFund":"-","CouponPaymentDetail":"1900-01-01T00:00:00","MatureDate":"1900-01-01T00:00:00","id":1,"CouponDetail":"-"}]}