{"ResultCount":1,"Search":{"KodeEmiten":"DFAM","EmitenType":null,"SortOrder":null,"SortColumn":null,"indexfrom":1,"pagesize":1},"Profiles":[{"Alamat":"Jl. Raung No.15, Gajahmungkur, Semarang - 50232","BAE":"PT. Sinartama Gunita","DataID":0,"Divisi":null,"EfekEmiten_EBA":false,"EfekEmiten_ETF":false,"EfekEmiten_Obligasi":false,"EfekEmiten_Saham":true,"EfekEmiten_SPEI":false,"Industri":"Pariwisata & Rekreasi","SubIndustri":"Hotel, Resor & Kapal Pesiar","Email":"corporate@dafamproperty.com","Fax":"-","id":0,"JenisEmiten":null,"KegiatanUsahaUtama":"Pengembangan Properti, Pengelolaan Gedung, Sewa Gedung , Perhotelandan Jasa Manajemen Hotel Melalui Entitas Anak","KodeDivisi":null,"KodeEmiten":"DFAM","NamaEmiten":"PT Dafam Property Indonesia Tbk","NPKP":"","NPWP":"02.768.793.8-512.000","PapanPencatatan":"Pengembangan","Sektor":"Barang Konsumen Non-Primer","SubSektor":"Jasa Konsumen","TanggalPencatatan":"2018-04-27T00:00:00","Telepon":"+6224 8312735 , +6224 8506459","Website":"www.dafamproperty.com","Status":0,"Logo":"/Portals/0/StaticData/ListedCompanies/LogoEmiten/DFAM.jpg"}],"Sekretaris":[{"Nama":"Soviadi Nor Rachman","Telepon":"+62 24 356 9595","Website":null,"Email":"corporate@dafamproperty.com","Fax":"","HP":"0856 4131 7848"}],"Direktur":[{"Nama":"Billy Dahlan","Jabatan":"DIREKTUR UTAMA","Afiliasi":true},{"Nama":"WIjaya Dahlan","Jabatan":"DIREKTUR","Afiliasi":true},{"Nama":"Andhy Irawan Kristyanto","Jabatan":"DIREKTUR","Afiliasi":true}],"Komisaris":[{"Nama":"Ferdinandus Soleh Dahlan","Jabatan":"KOMISARIS UTAMA","Independen":false},{"Nama":"Junaidi Dahlan","Jabatan":"KOMISARIS","Independen":false},{"Nama":"Jaeni, SE,Msi,Ak,CA","Jabatan":"KOMISARIS","Independen":true}],"KomiteAudit":[{"Jabatan":"KETUA","Nama":"Jaeni, SE,Msi,Ak,CA"},{"Jabatan":"ANGGOTA","Nama":"Siti Sundari"},{"Jabatan":"ANGGOTA","Nama":"Teguh Parmono Hadi"}],"PemegangSaham":[{"Jumlah":134032800.0,"Kategori":"Lebih dari 5%","Nama":"Reksa Dana Narada Saham Indonesia","Pengendali":false,"Persentase":7.1},{"Jumlah":1015000000.0,"Kategori":"Lebih dari 5%","Nama":"PT Dafam","Pengendali":true,"Persentase":53.4},{"Jumlah":131665073.0,"Kategori":"Lebih dari 5%","Nama":"Edy Selamat","Pengendali":false,"Persentase":7.0},{"Jumlah":185175000.0,"Kategori":"Lebih dari 5%","Nama":"Billy Dahlan","Pengendali":true,"Persentase":9.7},{"Jumlah":433979977.0,"Kategori":"Kurang dari 5%","Nama":"Masyarakat","Pengendali":false,"Persentase":22.8},{"Jumlah":0.0,"Kategori":"Saham Treasury","Nama":"Saham Treasury","Pengendali":false,"Persentase":0.0},{"Jumlah":185175000.0,"Kategori":"Direksi","Nama":"Billy Dahlan","Pengendali":true,"Persentase":9.7},{"Jumlah":4000000.0,"Kategori":"Direksi","Nama":"Andhy Irawan Kristyanto","Pengendali":false,"Persentase":0.21}],"AnakPerusahaan":[{"BidangUsaha":"Manajemen Hotel","JumlahAset":9813508549.0,"Lokasi":"Semarang, Jawa Tengah","MataUang":"IDR","Nama":"PT Dafam Hotel Management","Persentase":75.0,"Satuan":"PENUH","StatusOperasi":"Operasional","TahunKomersil":"2017"},{"BidangUsaha":"Perumahan/Residential","JumlahAset":48784821463.0,"Lokasi":"Semarang, Jawa Tengah","MataUang":"IDR","Nama":"PT Dafam Maju Bersama","Persentase":99.0,"Satuan":"PENUH","StatusOperasi":"Operasional","TahunKomersil":"2013"},{"BidangUsaha":"Hotel","JumlahAset":98529169735.0,"Lokasi":"Semarang, Jawa Tengah","MataUang":"IDR","Nama":"PT Dafam Mambo International","Persentase":99.0,"Satuan":"PENUH","StatusOperasi":"Operasional","TahunKomersil":"2009"}],"KAP":[{"AkhirPeriode":"1911-01-01T00:00:00","KAP1":"","Nama":"Morhan & Rekan","SigningPartner":"","TahunBuku":0,"TanggalTahunBuku":"2019-12-31T00:00:00","TglOpini":"1911-01-01T00:00:00"},{"AkhirPeriode":"1911-01-01T00:00:00","KAP1":"","Nama":"Morhan & Rekan","SigningPartner":"","TahunBuku":2017,"TanggalTahunBuku":"1911-01-01T00:00:00","TglOpini":"2018-02-05T00:00:00"},{"AkhirPeriode":"1911-01-01T00:00:00","KAP1":"","Nama":"Morhan & Rekan","SigningPartner":"","TahunBuku":0,"TanggalTahunBuku":"2020-12-31T00:00:00","TglOpini":"1911-01-01T00:00:00"},{"AkhirPeriode":"1911-01-01T00:00:00","KAP1":"","Nama":"Morhan & Rekan","SigningPartner":"","TahunBuku":2017,"TanggalTahunBuku":"1911-01-01T00:00:00","TglOpini":"2018-02-05T00:00:00"},{"AkhirPeriode":"1911-01-01T00:00:00","KAP1":"","Nama":"Morhan & Rekan","SigningPartner":"","TahunBuku":0,"TanggalTahunBuku":"2021-12-31T00:00:00","TglOpini":"1911-01-01T00:00:00"},{"AkhirPeriode":"1911-01-01T00:00:00","KAP1":"","Nama":"Morhan & Rekan","SigningPartner":"","TahunBuku":2017,"TanggalTahunBuku":"1911-01-01T00:00:00","TglOpini":"2018-02-05T00:00:00"},{"AkhirPeriode":"1911-01-01T00:00:00","KAP1":"","Nama":"Morhan & Rekan","SigningPartner":"","TahunBuku":0,"TanggalTahunBuku":"2022-12-31T00:00:00","TglOpini":"1911-01-01T00:00:00"},{"AkhirPeriode":"1911-01-01T00:00:00","KAP1":"","Nama":"Morhan & Rekan","SigningPartner":"","TahunBuku":2017,"TanggalTahunBuku":"1911-01-01T00:00:00","TglOpini":"2018-02-05T00:00:00"}],"Dividen":[],"BondsAndSukuk":[],"IssuedBond":[]}