{"ResultCount":1,"Search":{"KodeEmiten":"EMDE","EmitenType":null,"SortOrder":null,"SortColumn":null,"indexfrom":1,"pagesize":1},"Profiles":[{"Alamat":"The Bellagio Residence Mega Kuningan Jl. Mega Kuningan Barat IX Kav. E4 No. 3 Kuningan Timur, Setiabudi, Jakarta Selatan 12950","BAE":"PT. Adimitra Jasa Korpora","DataID":0,"Divisi":null,"EfekEmiten_EBA":false,"EfekEmiten_ETF":false,"EfekEmiten_Obligasi":false,"EfekEmiten_Saham":true,"EfekEmiten_SPEI":false,"Industri":"Pengelola & Pengembang Real Estat","SubIndustri":"Pengembang & Operator Real Estat","Email":"corporate.secretary@megapolitan-group.com","Fax":"30019939","id":0,"JenisEmiten":null,"KegiatanUsahaUtama":"Pengembangan Kawasan (Developer)","KodeDivisi":null,"KodeEmiten":"EMDE","NamaEmiten":"Megapolitan Developments Tbk","NPKP":"-","NPWP":"01.310.078.9-054.000","PapanPencatatan":"Pengembangan","Sektor":"Properti & Real Estat","SubSektor":"Properti & Real Estat","TanggalPencatatan":"2011-01-12T00:00:00","Telepon":"30019938","Website":"www.megapolitan-group.com","Status":0,"Logo":"/Portals/0/StaticData/ListedCompanies/LogoEmiten/EMDE.jpg"}],"Sekretaris":[{"Nama":"Ouw Desiyanti","Telepon":"021-30019938","Website":null,"Email":"corporate.secretary@megapolitan-group.com","Fax":"021-30019939","HP":"081519107619"}],"Direktur":[{"Nama":"LORA MELANI LOWAS BARAK RIMBA","Jabatan":"DIREKTUR UTAMA","Afiliasi":true},{"Nama":"RONALD TRISNA WIHARDJA","Jabatan":"DIREKTUR","Afiliasi":true},{"Nama":"RADIAN WENA WAHYUDI ST","Jabatan":"DIREKTUR","Afiliasi":false}],"Komisaris":[{"Nama":"BARBARA ANGELA BARAK RIMBA","Jabatan":"KOMISARIS UTAMA","Independen":false},{"Nama":"JENNIFER BARAK RIMBA","Jabatan":"KOMISARIS","Independen":false},{"Nama":"HONGISISILIA, SE","Jabatan":"KOMISARIS","Independen":true},{"Nama":"DRS. ANTON BACHRUL ALAM, SH","Jabatan":"KOMISARIS","Independen":true}],"KomiteAudit":[{"Jabatan":"KETUA","Nama":"Anton Bachrul Alam"},{"Jabatan":"ANGGOTA","Nama":"Wiljadi Tan"}],"PemegangSaham":[{"Jumlah":2237018320.0,"Kategori":"Lebih dari 5%","Nama":"PT Cosmopolitan Persada Developments","Pengendali":true,"Persentase":66.78},{"Jumlah":231147000.0,"Kategori":"Lebih dari 5%","Nama":"DBS Bank LTD SG-PB Clients","Pengendali":false,"Persentase":6.9},{"Jumlah":618853000.0,"Kategori":"Kurang dari 5%","Nama":"Masyarakat","Pengendali":false,"Persentase":18.46},{"Jumlah":131490840.0,"Kategori":"Kurang dari 5%","Nama":"L. Melani Lowas Rimba","Pengendali":false,"Persentase":3.93},{"Jumlah":131490840.0,"Kategori":"Kurang dari 5%","Nama":"Sudjono Barak Rimba","Pengendali":false,"Persentase":3.93},{"Jumlah":0.0,"Kategori":"Saham Treasury","Nama":"Saham Treasury","Pengendali":false,"Persentase":0.0},{"Jumlah":131490840.0,"Kategori":"Direksi","Nama":"Lora Melani Lowas Barak Rimba","Pengendali":true,"Persentase":3.93}],"AnakPerusahaan":[{"BidangUsaha":"Pembangunan perumahan","JumlahAset":102716643284.0,"Lokasi":"Cinere, Depok","MataUang":"IDR","Nama":"PT Graha Mentari Persada","Persentase":99.0,"Satuan":"PENUH","StatusOperasi":"Aktif","TahunKomersil":"2007"},{"BidangUsaha":"Pembangunan perumahan","JumlahAset":147283266625.0,"Lokasi":"Cinere, Depok","MataUang":"IDR","Nama":"PT Mega Limo Estate","Persentase":99.80000305,"Satuan":"PENUH","StatusOperasi":"Aktif","TahunKomersil":"1982"},{"BidangUsaha":"Pembangunan perumahan dan apartemen serta pusat perbelanjaan","JumlahAset":1254076945839.0,"Lokasi":"Cinere, Depok, Cijunti dan Purwakarta","MataUang":"IDR","Nama":"PT Mega Pasanggrahan Indah","Persentase":99.37999725,"Satuan":"PENUH","StatusOperasi":"Aktif","TahunKomersil":"1983"},{"BidangUsaha":"Pembangunan perumahan","JumlahAset":702681634563.0,"Lokasi":"Cimandala - Bogor","MataUang":"IDR","Nama":"PT Tirta Persada Developments","Persentase":99.75,"Satuan":"PENUH","StatusOperasi":"Aktif","TahunKomersil":"2007"},{"BidangUsaha":"Apartemen","JumlahAset":125748721325.0,"Lokasi":"Tangerang","MataUang":"IDR","Nama":"PT Titan Property","Persentase":99.98999786,"Satuan":"PENUH","StatusOperasi":"Aktif","TahunKomersil":"2006"}],"KAP":[],"Dividen":[{"Nama":"Megapolitan Developments Tbk","Jenis":"dt","TahunBuku":"2016","TotalSahamBonus":0.0,"CashDividenPerSahamMU":"IDR","CashDividenPerSaham":2.0,"TanggalCum":"2017-06-21T00:00:00","TanggalExRegulerDanNegosiasi":"2017-06-22T00:00:00","TanggalDPS":"2017-07-04T16:00:00","TanggalPembayaran":"2017-07-14T00:00:00","Rasio1":0,"Rasio2":0,"CashDividenTotalMU":"IDR","CashDividenTotal":6700000000.0}],"BondsAndSukuk":[],"IssuedBond":[]}