{"ResultCount":1,"Search":{"KodeEmiten":"HILL","EmitenType":null,"SortOrder":null,"SortColumn":null,"indexfrom":1,"pagesize":1},"Profiles":[{"Alamat":"Blok R2, Jl. Taman Modern No. 19\nRT.014/RW.006, Ujung Menteng, Kecamatan Cakung, Kota Jakarta Timur,\nDaerah Khusus Ibukota Jakarta 13960","BAE":"PT. Bima Registra","DataID":0,"Divisi":null,"EfekEmiten_EBA":false,"EfekEmiten_ETF":false,"EfekEmiten_Obligasi":false,"EfekEmiten_Saham":true,"EfekEmiten_SPEI":false,"Industri":"Pendukung Minyak, Gas & Batu Bara","SubIndustri":"Jasa & Perlengkapan Minyak, Gas & Batu Bara","Email":"corporate.secretary@hillcon.co.id","Fax":"(021) 4618457","id":0,"JenisEmiten":null,"KegiatanUsahaUtama":"Aktivitas perusahaan\nholding dan aktivitas konsultasi manajemen serta jasa pertambangan dan jasa konstruksi melalui perusahaan anak.","KodeDivisi":null,"KodeEmiten":"HILL","NamaEmiten":"PT Hillcon Tbk","NPKP":"","NPWP":"210391942006000","PapanPencatatan":"Utama","Sektor":"Energi","SubSektor":"Minyak, Gas & Batu Bara","TanggalPencatatan":"2023-03-01T00:00:00","Telepon":"(021) 4618458","Website":"www.hillcon.co.id","Status":0,"Logo":"/Portals/0/StaticData/ListedCompanies/LogoEmiten/HILL.jpg"}],"Sekretaris":[{"Nama":"Angela Surniati","Telepon":"(021) 4618458","Website":null,"Email":"corporate.secretary@hillcon.co.id","Fax":"","HP":""}],"Direktur":[{"Nama":"Hersan Qiu","Jabatan":"DIREKTUR UTAMA","Afiliasi":true},{"Nama":"Hermansyah","Jabatan":"DIREKTUR","Afiliasi":true},{"Nama":"Jaya Angdika","Jabatan":"DIREKTUR","Afiliasi":false},{"Nama":"Rudi Santoso","Jabatan":"DIREKTUR","Afiliasi":false},{"Nama":"Stanley Qiu","Jabatan":"DIREKTUR","Afiliasi":true}],"Komisaris":[{"Nama":"Tan Tjoe Liang","Jabatan":"KOMISARIS UTAMA","Independen":true},{"Nama":"Caecilia Sulistiowati","Jabatan":"KOMISARIS","Independen":false}],"KomiteAudit":[{"Jabatan":"KETUA","Nama":"Tan Tjoe Liang"},{"Jabatan":"ANGGOTA","Nama":"Herwan Ng"},{"Jabatan":"ANGGOTA","Nama":"Nadalia Shofia Audrina"}],"PemegangSaham":[{"Jumlah":2029860000.0,"Kategori":"Lebih dari 5%","Nama":"PT Hillcon Equity Management","Pengendali":true,"Persentase":68.85},{"Jumlah":476140000.0,"Kategori":"Lebih dari 5%","Nama":"PT Bukit Persada Indonesia","Pengendali":false,"Persentase":16.15},{"Jumlah":442300000.0,"Kategori":"Kurang dari 5%","Nama":"Masyarakat","Pengendali":false,"Persentase":15.0},{"Jumlah":0.0,"Kategori":"Saham Treasury","Nama":"Saham Treasury","Pengendali":false,"Persentase":0.0},{"Jumlah":0.0,"Kategori":"Komisaris","Nama":"Tan Tjoe Liang","Pengendali":false,"Persentase":0.0},{"Jumlah":0.0,"Kategori":"Komisaris","Nama":"Caecilia Sulistiowati","Pengendali":false,"Persentase":0.0},{"Jumlah":0.0,"Kategori":"Direksi","Nama":"Hersan Qiu","Pengendali":true,"Persentase":0.0},{"Jumlah":0.0,"Kategori":"Direksi","Nama":"Hermansyah","Pengendali":false,"Persentase":0.0},{"Jumlah":0.0,"Kategori":"Direksi","Nama":"Jaya Angdika","Pengendali":false,"Persentase":0.0},{"Jumlah":0.0,"Kategori":"Direksi","Nama":"Rudi Santoso","Pengendali":false,"Persentase":0.0},{"Jumlah":0.0,"Kategori":"Direksi","Nama":"Stanley Qiu","Pengendali":false,"Persentase":0.0}],"AnakPerusahaan":[{"BidangUsaha":"Perdagangan suku\ncadang, reparasi,\nsewa, dan aksesoris\nmobil","JumlahAset":34952.0,"Lokasi":"Jakarta","MataUang":"IDR","Nama":"PT Hillcon Industrial Assets","Persentase":80.0,"Satuan":"JUTAAN","StatusOperasi":"","TahunKomersil":""},{"BidangUsaha":"Real Estate","JumlahAset":118465.0,"Lokasi":"Jakarta","MataUang":"IDR","Nama":"PT Hillcon Jaya Land","Persentase":80.0,"Satuan":"JUTAAN","StatusOperasi":"","TahunKomersil":""},{"BidangUsaha":"Jasa pertambangan","JumlahAset":7537.0,"Lokasi":"Jakarta","MataUang":"IDR","Nama":"PT Hillcon Mining Indonesia","Persentase":80.0,"Satuan":"JUTAAN","StatusOperasi":"","TahunKomersil":""},{"BidangUsaha":"Jasa Kontruksi","JumlahAset":2844649.0,"Lokasi":"Jakarta","MataUang":"IDR","Nama":"PT Hillconjaya Sakti","Persentase":80.0,"Satuan":"JUTAAN","StatusOperasi":"","TahunKomersil":""},{"BidangUsaha":"Jasa Kontruksi","JumlahAset":6997.0,"Lokasi":"Manado","MataUang":"IDR","Nama":"PT Jaya Berkat Usaha","Persentase":51.0,"Satuan":"JUTAAN","StatusOperasi":"","TahunKomersil":""},{"BidangUsaha":"Perdagangan suku\ncadang, dan\naksesoris mobil","JumlahAset":26754.0,"Lokasi":"Jakarta","MataUang":"IDR","Nama":"PT Pawon Servis Tama","Persentase":90.0,"Satuan":"JUTAAN","StatusOperasi":"","TahunKomersil":""}],"KAP":[{"AkhirPeriode":"1911-01-01T00:00:00","KAP1":"","Nama":"Kanaka Puradiredja, Suhartono","SigningPartner":"","TahunBuku":0,"TanggalTahunBuku":"2022-07-31T00:00:00","TglOpini":"1911-01-01T00:00:00"},{"AkhirPeriode":"1911-01-01T00:00:00","KAP1":"","Nama":"Kanaka Puradiredja, Suhartono","SigningPartner":"","TahunBuku":2022,"TanggalTahunBuku":"1911-01-01T00:00:00","TglOpini":"2022-12-01T00:00:00"}],"Dividen":[],"BondsAndSukuk":[],"IssuedBond":[]}