{"ResultCount":1,"Search":{"KodeEmiten":"PDES","EmitenType":null,"SortOrder":null,"SortColumn":null,"indexfrom":1,"pagesize":1},"Profiles":[{"Alamat":"Panorama Building Lt. 4 Jl Tomang Raya No. 63 Jakarta 11440","BAE":"PT. Raya Saham Registra","DataID":0,"Divisi":null,"EfekEmiten_EBA":false,"EfekEmiten_ETF":false,"EfekEmiten_Obligasi":false,"EfekEmiten_Saham":true,"EfekEmiten_SPEI":false,"Industri":"Pariwisata & Rekreasi","SubIndustri":"Agen Perjalanan","Email":"corsec.pdes@panorama-destination.com","Fax":"021-56958586","id":0,"JenisEmiten":null,"KegiatanUsahaUtama":"Biro Perjalanan Wisata ","KodeDivisi":null,"KodeEmiten":"PDES","NamaEmiten":"Destinasi Tirta Nusantara Tbk","NPKP":"","NPWP":"01.955.084.7-054.000","PapanPencatatan":"Pengembangan","Sektor":"Barang Konsumen Non-Primer","SubSektor":"Jasa Konsumen","TanggalPencatatan":"2008-07-08T00:00:00","Telepon":"021-56958585","Website":"www.panorama-destination.com","Status":0,"Logo":"/Portals/0/StaticData/ListedCompanies/LogoEmiten/PDES.jpg"}],"Sekretaris":[{"Nama":"Sylvia Rafael Harnadi","Telepon":"56958585","Website":null,"Email":"corsec.pdes@panorama-destination.com","Fax":"56958586","HP":""}],"Direktur":[{"Nama":"Satrijanto Tirtawisata","Jabatan":"DIREKTUR UTAMA","Afiliasi":true},{"Nama":"Sylvia Rafael Harnadi","Jabatan":"DIREKTUR","Afiliasi":true},{"Nama":"Martini","Jabatan":"DIREKTUR","Afiliasi":true}],"Komisaris":[{"Nama":"Daniel Martinus","Jabatan":"KOMISARIS UTAMA","Independen":false},{"Nama":"Rocky Wisuda Praputranto","Jabatan":"KOMISARIS","Independen":false},{"Nama":"Daniel Martinus","Jabatan":"KOMISARIS","Independen":true}],"KomiteAudit":[{"Jabatan":"KETUA","Nama":"Augustine Constatine Robot"},{"Jabatan":"ANGGOTA","Nama":"AR Ardianto Sutanto"},{"Jabatan":"ANGGOTA","Nama":"Syarief Gunawan"}],"PemegangSaham":[{"Jumlah":450000000.0,"Kategori":"Lebih dari 5%","Nama":"PT.PANORAMA SENTRAWISATA TBK","Pengendali":true,"Persentase":62.94},{"Jumlah":50000000.0,"Kategori":"Lebih dari 5%","Nama":"PT.CATUR PUTRA NUSANTARA","Pengendali":false,"Persentase":6.99},{"Jumlah":215000000.0,"Kategori":"Kurang dari 5%","Nama":"Masyarakat","Pengendali":false,"Persentase":30.07},{"Jumlah":0.0,"Kategori":"Saham Treasury","Nama":"Saham Treasury","Pengendali":false,"Persentase":0.0},{"Jumlah":11000.0,"Kategori":"Direksi","Nama":"MARTINI","Pengendali":false,"Persentase":0.0},{"Jumlah":0.0,"Kategori":"Komisaris","Nama":"DANIEL MARTINUS","Pengendali":false,"Persentase":0.0},{"Jumlah":24905000.0,"Kategori":"Direksi","Nama":"SATRIJANTO TIRTAWISATA","Pengendali":false,"Persentase":3.48},{"Jumlah":1400.0,"Kategori":"Direksi","Nama":"SYLVIA RAFAEL HARNADI","Pengendali":false,"Persentase":0.0}],"AnakPerusahaan":[{"BidangUsaha":"Jasa Perjalanan Wisata","JumlahAset":0.0,"Lokasi":"Vietnam","MataUang":"","Nama":"Panorama Destination (Vietnam) JV Ltd","Persentase":68.0,"Satuan":"","StatusOperasi":"Belum beroperasi","TahunKomersil":""},{"BidangUsaha":"Jasa Perjalanan Wisata","JumlahAset":9730833000.0,"Lokasi":"Kuala Lumpur","MataUang":"IDR","Nama":"Panorama Destination(M) Sdn Bhd","Persentase":100.0,"Satuan":"PENUH","StatusOperasi":"Operasi","TahunKomersil":"2019"},{"BidangUsaha":"Jasa Perjalanan Wisata","JumlahAset":10997478656.0,"Lokasi":"Singapura","MataUang":"IDR","Nama":"Panorama Destination(S) Pte.Ltd (PD)","Persentase":100.0,"Satuan":"PENUH","StatusOperasi":"Operasi","TahunKomersil":"2009"},{"BidangUsaha":"Biro Perjalanan Wisata","JumlahAset":18422696357.0,"Lokasi":"Jakarta","MataUang":"IDR","Nama":"PT Buaya Travel Indonesia","Persentase":80.0,"Satuan":"PENUH","StatusOperasi":"Operasi","TahunKomersil":"2015"},{"BidangUsaha":"Biro Perjalanan","JumlahAset":11000011608.0,"Lokasi":"Yogyakarta","MataUang":"IDR","Nama":"PT Destinasi Garuda Wisata","Persentase":51.0,"Satuan":"PENUH","StatusOperasi":"Operasi","TahunKomersil":"2002"},{"BidangUsaha":"Perdagangan Umum","JumlahAset":139620060579.0,"Lokasi":"Jakarta","MataUang":"IDR","Nama":"PT Graha Destinasi","Persentase":90.0,"Satuan":"PENUH","StatusOperasi":"Praoperasi","TahunKomersil":"2014"}],"KAP":[],"Dividen":[{"Nama":"Destinasi Tirta Nusantara Tbk","Jenis":"dt","TahunBuku":"2016","TotalSahamBonus":0.0,"CashDividenPerSahamMU":"IDR","CashDividenPerSaham":35.0,"TanggalCum":"2017-06-19T00:00:00","TanggalExRegulerDanNegosiasi":"2017-06-20T00:00:00","TanggalDPS":"2017-06-22T16:00:00","TanggalPembayaran":"2017-07-14T00:00:00","Rasio1":0,"Rasio2":0,"CashDividenTotalMU":"IDR","CashDividenTotal":25239500000.0}],"BondsAndSukuk":[],"IssuedBond":[]}