{"ResultCount":1,"Search":{"KodeEmiten":"PICO","EmitenType":null,"SortOrder":null,"SortColumn":null,"indexfrom":1,"pagesize":1},"Profiles":[{"Alamat":"JL. DAAN MOGOT KM. 14 KALIDERES JAKARTA BARAT","BAE":"PT. Ficomindo Buana Registrar","DataID":0,"Divisi":null,"EfekEmiten_EBA":false,"EfekEmiten_ETF":false,"EfekEmiten_Obligasi":false,"EfekEmiten_Saham":true,"EfekEmiten_SPEI":false,"Industri":"Wadah & Kemasan","SubIndustri":"Wadah & Kemasan","Email":"corpsec@pic.co.id","Fax":"(021) 6193446","id":0,"JenisEmiten":null,"KegiatanUsahaUtama":"Metal and Alied Products","KodeDivisi":null,"KodeEmiten":"PICO","NamaEmiten":"Pelangi Indah Canindo Tbk","NPKP":"","NPWP":"01.367.344.7-054.000 ","PapanPencatatan":"Pengembangan","Sektor":"Barang Baku","SubSektor":"Barang Baku","TanggalPencatatan":"1996-09-23T00:00:00","Telepon":"(021) 6192222","Website":"0","Status":0,"Logo":"/Portals/0/StaticData/ListedCompanies/LogoEmiten/PICO.jpg"}],"Sekretaris":[{"Nama":"ANTON","Telepon":"(021)619222","Website":null,"Email":"corpsec@pic.co.id","Fax":"-","HP":""}],"Direktur":[{"Nama":"KO DANDY","Jabatan":"DIREKTUR UTAMA","Afiliasi":false},{"Nama":"RUBIANTO","Jabatan":"DIREKTUR","Afiliasi":false}],"Komisaris":[{"Nama":"DARMINTO DARMADJI","Jabatan":"KOMISARIS UTAMA","Independen":false},{"Nama":"AMAN SANTOSO","Jabatan":"KOMISARIS","Independen":true}],"KomiteAudit":[],"PemegangSaham":[{"Jumlah":196177140.0,"Kategori":"Lebih dari 5%","Nama":"PT CITRAJAYA PERKASAMULIA","Pengendali":true,"Persentase":34.515},{"Jumlah":107786052.0,"Kategori":"Lebih dari 5%","Nama":"PT SARANAMULIA MAHARDHIKA","Pengendali":false,"Persentase":18.964},{"Jumlah":74307693.0,"Kategori":"Lebih dari 5%","Nama":"PT. KOEXIM MANDIRI FINANCE","Pengendali":false,"Persentase":13.074},{"Jumlah":190104115.0,"Kategori":"Kurang dari 5%","Nama":"Masyarakat","Pengendali":false,"Persentase":33.447},{"Jumlah":0.0,"Kategori":"Saham Treasury","Nama":"Saham Treasury","Pengendali":false,"Persentase":0.0},{"Jumlah":142500.0,"Kategori":"Direksi","Nama":"Ko Dandy","Pengendali":true,"Persentase":0.03}],"AnakPerusahaan":[{"BidangUsaha":"","JumlahAset":0.0,"Lokasi":"","MataUang":"","Nama":"","Persentase":0.0,"Satuan":"","StatusOperasi":"","TahunKomersil":""}],"KAP":[],"Dividen":[{"Nama":"Pelangi Indah Canindo Tbk","Jenis":"dt","TahunBuku":"2018","TotalSahamBonus":0.0,"CashDividenPerSahamMU":"IDR","CashDividenPerSaham":5.0,"TanggalCum":"2019-06-25T00:00:00","TanggalExRegulerDanNegosiasi":"2019-06-26T00:00:00","TanggalDPS":"2019-06-27T16:00:00","TanggalPembayaran":"2019-07-19T00:00:00","Rasio1":0,"Rasio2":0,"CashDividenTotalMU":"IDR","CashDividenTotal":2841875000.0}],"BondsAndSukuk":[],"IssuedBond":[]}