{"ResultCount":1,"Search":{"KodeEmiten":"TBMS","EmitenType":null,"SortOrder":null,"SortColumn":null,"indexfrom":1,"pagesize":1},"Profiles":[{"Alamat":"\tJl.Daan Mogot Km. 16 Jakarta Barat ","BAE":"PT. Sirca Datapro Perdana","DataID":0,"Divisi":null,"EfekEmiten_EBA":false,"EfekEmiten_ETF":false,"EfekEmiten_Obligasi":false,"EfekEmiten_Saham":true,"EfekEmiten_SPEI":false,"Industri":"Logam & Mineral","SubIndustri":"Tembaga","Email":"         rini@pttms.co.id ","Fax":"        (021)6190135 ","id":0,"JenisEmiten":null,"KegiatanUsahaUtama":"Industri Kawat Tembaga ","KodeDivisi":null,"KodeEmiten":"TBMS","NamaEmiten":"Tembaga Mulia Semanan Tbk","NPKP":"\t01.000.137.8-092.000 ","NPWP":"\t01.000.137.8-092.000 ","PapanPencatatan":"Pengembangan","Sektor":"Barang Baku","SubSektor":"Barang Baku","TanggalPencatatan":"1990-05-23T00:00:00","Telepon":"\t(021)6190131 ","Website":"\twww.pttms.co.id ","Status":0,"Logo":"/Portals/0/StaticData/ListedCompanies/LogoEmiten/TBMS.jpg"}],"Sekretaris":[{"Nama":"Erni Yunita Sari","Telepon":"021.6190128","Website":null,"Email":"erni@pttms.co.id","Fax":"021.5452567","HP":""}],"Direktur":[{"Nama":"KENJI YAMAGUCHI","Jabatan":"PRESIDEN DIREKTUR","Afiliasi":true},{"Nama":"TAKAAKI OKU","Jabatan":"DIREKTUR","Afiliasi":true},{"Nama":"MITSURU YANASE","Jabatan":"DIREKTUR","Afiliasi":true},{"Nama":"HERRY CAHYO TRI YUNIARTO","Jabatan":"DIREKTUR","Afiliasi":true},{"Nama":"HENGKY KARTASASMITA","Jabatan":"DIREKTUR","Afiliasi":false}],"Komisaris":[{"Nama":"BAYU ADIWIJAYA SOEPONO","Jabatan":"PRESIDEN KOMISARIS","Independen":false},{"Nama":"MASAO TERAUCHI","Jabatan":"KOMISARIS","Independen":false},{"Nama":"SHIGERU NAKASHIMA","Jabatan":"KOMISARIS","Independen":false},{"Nama":"DEWA NYOMAN ADNYANA","Jabatan":"KOMISARIS","Independen":true},{"Nama":"WANTINA DHARMAWI","Jabatan":"KOMISARIS","Independen":true}],"KomiteAudit":[{"Jabatan":"KETUA","Nama":"Wantina Dharmawi"},{"Jabatan":"ANGGOTA","Nama":"Yanti Widjaya"},{"Jabatan":"ANGGOTA","Nama":"Yacintha Susita Dewi"}],"PemegangSaham":[{"Jumlah":155820000.0,"Kategori":"Lebih dari 5%","Nama":"THE FURUKAWA ELECTRIC  CO.LTD","Pengendali":true,"Persentase":42.42},{"Jumlah":124200000.0,"Kategori":"Lebih dari 5%","Nama":"PT SUPREME CABLE MANUFACTURING CORP ","Pengendali":true,"Persentase":33.81},{"Jumlah":36734000.0,"Kategori":"Lebih dari 5%","Nama":"TOYOTA TSUSHO CORPORATION","Pengendali":false,"Persentase":10.0},{"Jumlah":50586000.0,"Kategori":"Kurang dari 5%","Nama":"Masyarakat","Pengendali":false,"Persentase":13.77},{"Jumlah":0.0,"Kategori":"Saham Treasury","Nama":"Saham Treasury","Pengendali":false,"Persentase":0.0},{"Jumlah":0.0,"Kategori":"Komisaris","Nama":"BAYU ADIWIJAYA SOEPONO","Pengendali":false,"Persentase":0.0},{"Jumlah":0.0,"Kategori":"Komisaris","Nama":"MASAO TERAUCHI","Pengendali":false,"Persentase":0.0},{"Jumlah":0.0,"Kategori":"Komisaris","Nama":"SHIGERU NAKASHISMA","Pengendali":false,"Persentase":0.0},{"Jumlah":0.0,"Kategori":"Komisaris","Nama":"DEWA NYOMAN ADNYANA","Pengendali":false,"Persentase":0.0},{"Jumlah":0.0,"Kategori":"Komisaris","Nama":"WANTINA DHARMAWI","Pengendali":false,"Persentase":0.0},{"Jumlah":0.0,"Kategori":"Direksi","Nama":"KENJI YAMAGUCHI","Pengendali":false,"Persentase":0.0},{"Jumlah":0.0,"Kategori":"Direksi","Nama":"TAKAAKI OKU","Pengendali":false,"Persentase":0.0},{"Jumlah":0.0,"Kategori":"Direksi","Nama":"MITSURU YANASE","Pengendali":false,"Persentase":0.0},{"Jumlah":0.0,"Kategori":"Direksi","Nama":"HERRY CAHYO TRI YUNIARTO","Pengendali":false,"Persentase":0.0},{"Jumlah":0.0,"Kategori":"Direksi","Nama":"HENGKY KARTASASMITA","Pengendali":false,"Persentase":0.0}],"AnakPerusahaan":[{"BidangUsaha":"","JumlahAset":0.0,"Lokasi":"","MataUang":"","Nama":"","Persentase":0.0,"Satuan":"","StatusOperasi":"","TahunKomersil":""}],"KAP":[],"Dividen":[{"Nama":"Tembaga Mulia Semanan Tbk","Jenis":"dt","TahunBuku":"2021","TotalSahamBonus":0.0,"CashDividenPerSahamMU":"","CashDividenPerSaham":0.0,"TanggalCum":"2022-06-17T00:00:00","TanggalExRegulerDanNegosiasi":"2022-06-20T00:00:00","TanggalDPS":"2022-06-21T16:00:00","TanggalPembayaran":"2022-07-08T00:00:00","Rasio1":0,"Rasio2":0,"CashDividenTotalMU":"","CashDividenTotal":0.0}],"BondsAndSukuk":[],"IssuedBond":[]}