{"ResultCount":1,"Search":{"KodeEmiten":"TURI","EmitenType":null,"SortOrder":null,"SortColumn":null,"indexfrom":1,"pagesize":1},"Profiles":[{"Alamat":"Gedung Tunas Toyota Lantai 3 Jl Raya Pasar Minggu No 7 Jakarta","BAE":"PT. Datindo Entrycom","DataID":0,"Divisi":null,"EfekEmiten_EBA":false,"EfekEmiten_ETF":false,"EfekEmiten_Obligasi":false,"EfekEmiten_Saham":true,"EfekEmiten_SPEI":false,"Industri":"Ritel Khusus","SubIndustri":"Ritel Otomotif","Email":"dewi.yunita@tunasgroup.com","Fax":"(021) 799 562","id":0,"JenisEmiten":null,"KegiatanUsahaUtama":"Distribusi dan Agen Penjualan Kend. Bermotor","KodeDivisi":null,"KodeEmiten":"TURI","NamaEmiten":"Tunas Ridean Tbk","NPKP":"","NPWP":"01.310.233.0-054.000","PapanPencatatan":"Utama","Sektor":"Barang Konsumen Non-Primer","SubSektor":"Perdagangan Ritel","TanggalPencatatan":"1995-05-16T00:00:00","Telepon":"(021) 794 4788; 794 0555","Website":"www.tunasgroup.com","Status":0,"Logo":"/Portals/0/StaticData/ListedCompanies/LogoEmiten/TURI.jpg"}],"Sekretaris":[{"Nama":"Dewi Yunita","Telepon":"(021) 7944788","Website":null,"Email":"dewi.yunita@tunasgroup.com","Fax":"(021) 7995621","HP":"081806500003"}],"Direktur":[{"Nama":"Rico Adisurja Setiawan","Jabatan":"DIREKTUR UTAMA","Afiliasi":true},{"Nama":"Nugraha Indra Permadi","Jabatan":"DIREKTUR","Afiliasi":true},{"Nama":"Andrew Ling Hua Chan","Jabatan":"DIREKTUR","Afiliasi":true},{"Nama":"Tenny Febyana Halim","Jabatan":"DIREKTUR","Afiliasi":true},{"Nama":"Ester Tanudjaja","Jabatan":"DIREKTUR","Afiliasi":true}],"Komisaris":[{"Nama":"Anton Setiawan","Jabatan":"KOMISARIS UTAMA","Independen":false},{"Nama":"DR Arie Setiabudi Soesilo, M.Sc","Jabatan":"WAKIL KOMISARIS UTAMA","Independen":true},{"Nama":"Sarastri Baskoro","Jabatan":"KOMISARIS","Independen":true},{"Nama":"Hong Anton Leoman","Jabatan":"KOMISARIS","Independen":false},{"Nama":"Wilfrid Foo Tsu Jin","Jabatan":"KOMISARIS","Independen":false}],"KomiteAudit":[{"Jabatan":"KETUA","Nama":"Sarastri Baskoro"},{"Jabatan":"ANGGOTA","Nama":"Hardi Montana"},{"Jabatan":"ANGGOTA","Nama":"Hanifah Purnama"}],"PemegangSaham":[{"Jumlah":2580009000.0,"Kategori":"Lebih dari 5%","Nama":"Jardine Cycle & Carriage Limited","Pengendali":false,"Persentase":46.24},{"Jumlah":2580009000.0,"Kategori":"Lebih dari 5%","Nama":"PT Tunas Andalan Pratama","Pengendali":true,"Persentase":46.24},{"Jumlah":418634922.0,"Kategori":"Lebih dari 5%","Nama":"PT Tunas Ridean Tbk","Pengendali":false,"Persentase":7.5},{"Jumlah":1347078.0,"Kategori":"Kurang dari 5%","Nama":"Pemegang Saham Lainnya","Pengendali":false,"Persentase":0.02},{"Jumlah":0.0,"Kategori":"Saham Treasury","Nama":"Saham Treasury","Pengendali":false,"Persentase":0.0},{"Jumlah":0.0,"Kategori":"Direksi","Nama":"Rico Adisurja Setiawan","Pengendali":false,"Persentase":0.0}],"AnakPerusahaan":[{"BidangUsaha":"Otomotif","JumlahAset":137352.0,"Lokasi":"Pangkal Pinang","MataUang":"IDR","Nama":"PT Asia Surya Perkasa","Persentase":87.5,"Satuan":"JUTAAN","StatusOperasi":"Aktif","TahunKomersil":"2015"},{"BidangUsaha":"Jasa sewa","JumlahAset":47365.0,"Lokasi":"Jakarta","MataUang":"IDR","Nama":"PT Mega Armada Sudeco","Persentase":100.0,"Satuan":"JUTAAN","StatusOperasi":"Aktif","TahunKomersil":"2014"},{"BidangUsaha":"Jasa sewa","JumlahAset":12093.0,"Lokasi":"Jakarta","MataUang":"IDR","Nama":"PT Mitra Ananta Megah","Persentase":100.0,"Satuan":"JUTAAN","StatusOperasi":"Aktif","TahunKomersil":"2014"},{"BidangUsaha":"Jasa sewa","JumlahAset":21386.0,"Lokasi":"Jakarta","MataUang":"IDR","Nama":"PT Mitra Asri Pratama","Persentase":100.0,"Satuan":"JUTAAN","StatusOperasi":"Aktif","TahunKomersil":"2013"},{"BidangUsaha":"Otomotif","JumlahAset":60418.0,"Lokasi":"Jakarta","MataUang":"IDR","Nama":"PT Rahardja Ekalancar","Persentase":100.0,"Satuan":"JUTAAN","StatusOperasi":"Aktif","TahunKomersil":"1990"},{"BidangUsaha":"Otomotif","JumlahAset":37253.0,"Lokasi":"Jakarta","MataUang":"IDR","Nama":"PT Surya Mobil Megahtama","Persentase":100.0,"Satuan":"JUTAAN","StatusOperasi":"Aktif","TahunKomersil":"1997"},{"BidangUsaha":"Jasa sewa","JumlahAset":1207935.0,"Lokasi":"Jakarta","MataUang":"IDR","Nama":"PT Surya Sudeco","Persentase":100.0,"Satuan":"MILYARAN","StatusOperasi":"Aktif","TahunKomersil":"1989"},{"BidangUsaha":"Otomotif","JumlahAset":10774.0,"Lokasi":"Jakarta","MataUang":"IDR","Nama":"PT Tunas Asset Sarana","Persentase":100.0,"Satuan":"JUTAAN","StatusOperasi":"Aktif","TahunKomersil":"2002"},{"BidangUsaha":"Otomotif","JumlahAset":737987.0,"Lokasi":"Lampung","MataUang":"IDR","Nama":"PT Tunas Dwipa Matra","Persentase":100.0,"Satuan":"JUTAAN","StatusOperasi":"Aktif","TahunKomersil":"1984"},{"BidangUsaha":"Otomotif","JumlahAset":860617.0,"Lokasi":"Jakarta","MataUang":"IDR","Nama":"PT Tunas Mobilindo Parama","Persentase":100.0,"Satuan":"JUTAAN","StatusOperasi":"Aktif","TahunKomersil":"1984"},{"BidangUsaha":"Otomotif","JumlahAset":976309.0,"Lokasi":"Jakarta","MataUang":"IDR","Nama":"PT Tunas Mobilindo Perkasa","Persentase":100.0,"Satuan":"JUTAAN","StatusOperasi":"Aktif","TahunKomersil":"1986"}],"KAP":[],"Dividen":[{"Nama":"Tunas Ridean Tbk","Jenis":"dt","TahunBuku":"2021","TotalSahamBonus":0.0,"CashDividenPerSahamMU":"","CashDividenPerSaham":0.0,"TanggalCum":"2022-05-27T00:00:00","TanggalExRegulerDanNegosiasi":"2022-05-30T00:00:00","TanggalDPS":"2022-05-31T16:00:00","TanggalPembayaran":"2022-06-17T00:00:00","Rasio1":0,"Rasio2":0,"CashDividenTotalMU":"IDR","CashDividenTotal":267840000000.0}],"BondsAndSukuk":[],"IssuedBond":[]}